LICENSE
MANIFEST.in
README.MD
README.md
setup.py
libpythonpronew/__init__.py
libpythonpronew/github_api.py
libpythonpronew/tests/__init__.py
libpythonpronew/tests/test_exemplo.py
libpythonpronew/tests/Test_spam/__init__.py
libpythonpronew/tests/Test_spam/conftest.py
libpythonpronew/tests/Test_spam/test_enviador_de_email.py
libpythonpronew/tests/Test_spam/test_envio_para_base_de_usuarios.py
libpythonpronew/tests/Test_spam/test_github_api.py
libpythonpronew/tests/Test_spam/test_usuarios.py
libpythonpronew_ghc.egg-info/PKG-INFO
libpythonpronew_ghc.egg-info/SOURCES.txt
libpythonpronew_ghc.egg-info/dependency_links.txt
libpythonpronew_ghc.egg-info/not-zip-safe
libpythonpronew_ghc.egg-info/requires.txt
libpythonpronew_ghc.egg-info/top_level.txt
spam/__init__.py
spam/db.py
spam/enviador_de_email.py
spam/main.py
spam/modelos.py